{"CLASS": {"n_components": null, "alpha": 1, "n_iter": 1000, "fit_algorithm": "lars", "n_jobs": null, "batch_size": 3, "shuffle": true, "dict_init": null, "transform_algorithm": "omp", "transform_n_nonzero_coefs": null, "transform_alpha": null, "verbose": false, "split_sign": false, "random_state": null, "positive_code": false, "positive_dict": false}, "FIT": {"X": null, "y": null}, "META": {"sklearn_version": "0.21.3", "classifier": "sklearn.decomposition.dict_learning.MiniBatchDictionaryLearning"}}